Colosseum_client-0.0.1.data/data/LICENSE.txt
colosseum/__init__.py
colosseum/game_client.py
colosseum/testAgentKaanEdit.py
colosseum/test_agent.py
envs/__init__.py
envs/envs_list.py
utils/__init__.py
utils/compress.py
utils/socket_wrap.py
utils/test_compression.py
Colosseum_client-0.0.1.dist-info/LICENSE.txt
Colosseum_client-0.0.1.dist-info/METADATA
Colosseum_client-0.0.1.dist-info/WHEEL
Colosseum_client-0.0.1.dist-info/top_level.txt
Colosseum_client-0.0.1.dist-info/RECORD
